apidoc2runner/__init__.py
apidoc2runner/cli.py
apidoc2runner/compat.py
apidoc2runner/core.py
apidoc2runner/parser.py
apidoc2runner/utils.py
tests/__init__.py
tests/test_postmanparser.py
apidoc2runner-0.0.1.dist-info/LICENSE
apidoc2runner-0.0.1.dist-info/METADATA
apidoc2runner-0.0.1.dist-info/WHEEL
apidoc2runner-0.0.1.dist-info/entry_points.txt
apidoc2runner-0.0.1.dist-info/top_level.txt
apidoc2runner-0.0.1.dist-info/RECORD
