Metadata-Version: 2.1
Name: apidoc2runner
Version: 0.0.1
Summary: Convert apidoc data to JSON testcases for HttpRunner.
Home-page: https://github.com/gerrywen/apidoc2runner
Author: gerrywen
Author-email: blog@gerrywen.com
License: MIT
Keywords: apidoc converter json
Platform: UNKNOWN
Classifier: Development Status :: 3 - Alpha
Classifier: Programming Language :: Python :: 2.7
Classifier: Programming Language :: Python :: 3.4
Classifier: Programming Language :: Python :: 3.5
Classifier: Programming Language :: Python :: 3.6
Classifier: Programming Language :: Python :: 3.7
